{
  "project_info": {
    "project_number": "207729078237",
    "firebase_url": "https://modul-6-f5ed6.firebaseio.com",
    "project_id": "modul-6-f5ed6",
    "storage_bucket": "modul-6-f5ed6.appspot.com"
  },
  "client": [
    {
      "client_info": {
        "mobilesdk_app_id": "1:207729078237:android:9c788dfecd08c639",
        "android_client_info": {
          "package_name": "com.example.android.idaayuanila_1202150280_modul6"
        }
      },
      "oauth_client": [
        {
          "client_id": "207729078237-ke7k7nll5a22ajdf1kevhpadhsfrfum0.apps.googleusercontent.com",
          "client_type": 3
        }
      ],
      "api_key": [
        {
          "current_key": "AIzaSyA8MsbPXtMWFlOu8dTMhVvU4xCDxNoJ6PA"
        }
      ],
      "services": {
        "analytics_service": {
          "status": 1
        },
        "appinvite_service": {
          "status": 1,
          "other_platform_oauth_client": []
        },
        "ads_service": {
          "status": 2
        }
      }
    }
  ],
  "configuration_version": "1"
}